{
  "id": "https://www.w3id.org/KulturVok/terms/grobsystematik/D6651G",
  "type": "Concept",
  "prefLabel": {
    "de": "Gratsägen"
  },
  "altLabel": {
    "de": [
      "Sägen (Grat-)"
    ]
  },
  "notation": [
    "D6651G"
  ],
  "narrower": [
    {
      "id": "https://www.w3id.org/KulturVok/terms/grobsystematik/A79C4F",
      "prefLabel": {
        "de": "Lochsäge mit Griff"
      }
    },
    {
      "id": "https://www.w3id.org/KulturVok/terms/grobsystematik/AFFGD6",
      "prefLabel": {
        "de": "Gratsäge mit zwei Wänden"
      }
    },
    {
      "id": "https://www.w3id.org/KulturVok/terms/grobsystematik/BG2CC1",
      "prefLabel": {
        "de": "Baumsäge zum Schrauben"
      }
    },
    {
      "id": "https://www.w3id.org/KulturVok/terms/grobsystematik/C2839B",
      "prefLabel": {
        "de": "Metallbogensäge"
      }
    },
    {
      "id": "https://www.w3id.org/KulturVok/terms/grobsystematik/CA7236",
      "prefLabel": {
        "de": "Adernsäge, verstellbar"
      }
    },
    {
      "id": "https://www.w3id.org/KulturVok/terms/grobsystematik/CB8724",
      "prefLabel": {
        "de": "Fuchsschwanz ohne Rücken"
      }
    },
    {
      "id": "https://www.w3id.org/KulturVok/terms/grobsystematik/CC3CGD",
      "prefLabel": {
        "de": "Stiftsäge"
      }
    },
    {
      "id": "https://www.w3id.org/KulturVok/terms/grobsystematik/DBFF9F",
      "prefLabel": {
        "de": "Lochsäge mit Heft"
      }
    },
    {
      "id": "https://www.w3id.org/KulturVok/terms/grobsystematik/DGG63F",
      "prefLabel": {
        "de": "Fuchsschwanz mit Rücken"
      }
    },
    {
      "id": "https://www.w3id.org/KulturVok/terms/grobsystematik/F3B38B",
      "prefLabel": {
        "de": "Gratsäge mit Wand"
      }
    },
    {
      "id": "https://www.w3id.org/KulturVok/terms/grobsystematik/F726F3",
      "prefLabel": {
        "de": "Metallsäge mit Holzfassung"
      }
    },
    {
      "id": "https://www.w3id.org/KulturVok/terms/grobsystematik/F92CBA",
      "prefLabel": {
        "de": "Nutsäge, verstellbar"
      }
    },
    {
      "id": "https://www.w3id.org/KulturVok/terms/grobsystematik/F94171",
      "prefLabel": {
        "de": "Metallsäge mit Eisenbogen"
      }
    },
    {
      "id": "https://www.w3id.org/KulturVok/terms/grobsystematik/B1G668",
      "prefLabel": {
        "de": "Baumsäge"
      }
    },
    {
      "id": "https://www.w3id.org/KulturVok/terms/grobsystematik/B2926B",
      "prefLabel": {
        "de": "Laubsägebogen"
      }
    }
  ],
  "broader": {
    "id": "https://www.w3id.org/KulturVok/terms/grobsystematik/B126D7",
    "prefLabel": {
      "de": "Gefaßte Sägen"
    }
  },
  "inScheme": [
    {
      "id": "https://www.w3id.org/KulturVok/terms/grobsystematik",
      "title": {
        "de": "Grobsystematik"
      }
    }
  ],
  "inSchemeAll": [
    {
      "id": "https://www.w3id.org/KulturVok/terms/grobsystematik"
    }
  ],
  "@context": {
    "@version": 1.1,
    "id": "@id",
    "type": "@type",
    "@vocab": "http://www.w3.org/2004/02/skos/core#",
    "xsd": "http://www.w3.org/2001/XMLSchema#",
    "dct": "http://purl.org/dc/terms/",
    "dc": "http://purl.org/dc/elements/1.1/",
    "schema": "https://schema.org/",
    "vann": "http://purl.org/vocab/vann/",
    "ldp": "http://www.w3.org/ns/ldp#",
    "owl": "http://www.w3.org/2002/07/owl#",
    "rdfs": "http://www.w3.org/2000/01/rdf-schema#",
    "ex": "http://www.example.com/",
    "title": {
      "@id": "dct:title",
      "@container": "@language"
    },
    "dc:title": {
      "@id": "dc:title",
      "@container": "@language"
    },
    "dc:description": {
      "@id": "dc:description",
      "@container": "@language"
    },
    "description": {
      "@id": "dct:description",
      "@container": "@language"
    },
    "license": {
      "@id": "dct:license",
      "@container": "@language"
    },
    "issued": {
      "@id": "dct:issued",
      "@type": "xsd:date"
    },
    "created": {
      "@id": "dct:created",
      "@type": "xsd:date"
    },
    "modified": {
      "@id": "dct:modified",
      "@type": "xsd:date"
    },
    "creator": {
      "@id": "dct:creator",
      "@container": "@set"
    },
    "contributor": {
      "@id": "dct:contributor",
      "@container": "@set"
    },
    "subject": {
      "@id": "dct:subject",
      "@container": [
        "@language",
        "@set"
      ]
    },
    "rights": {
      "@id": "dct:rights",
      "@container": "@set"
    },
    "publisher": "dct:publisher",
    "preferredNamespacePrefix": "vann:preferredNamespacePrefix",
    "preferredNamespaceUri": "vann:preferredNamespaceUri",
    "isBasedOn": "schema:isBasedOn",
    "conceptCount": "ex:conceptCount",
    "source": {
      "@id": "dct:source",
      "@container": "@set"
    },
    "prefLabel": {
      "@container": "@language"
    },
    "altLabel": {
      "@container": [
        "@language",
        "@set"
      ]
    },
    "hiddenLabel": {
      "@container": [
        "@language",
        "@set"
      ]
    },
    "definition": {
      "@container": "@language"
    },
    "note": {
      "@container": [
        "@language",
        "@set"
      ]
    },
    "changeNote": {
      "@container": [
        "@language",
        "@set"
      ]
    },
    "editorialNote": {
      "@container": [
        "@language",
        "@set"
      ]
    },
    "historyNote": {
      "@container": [
        "@language",
        "@set"
      ]
    },
    "scopeNote": {
      "@container": [
        "@language",
        "@set"
      ]
    },
    "notation": {
      "@container": "@set"
    },
    "example": {
      "@container": "@language"
    },
    "narrower": {
      "@container": "@set"
    },
    "related": {
      "@container": "@set"
    },
    "relatedMatch": {
      "@container": "@set"
    },
    "narrowerTransitive": {
      "@container": "@set"
    },
    "broaderTransitive": {
      "@container": "@set"
    },
    "broadMatch": {
      "@container": "@set"
    },
    "narrowMatch": {
      "@container": "@set"
    },
    "closeMatch": {
      "@container": "@set"
    },
    "exactMatch": {
      "@container": "@set"
    },
    "hasTopConcept": {
      "@container": "@set"
    },
    "inScheme": {
      "@container": "@set"
    },
    "topConceptOf": {
      "@container": "@set"
    },
    "deprecated": {
      "@id": "owl:deprecated",
      "@type": "xsd:boolean"
    },
    "isReplacedBy": {
      "@id": "dct:isReplacedBy",
      "@container": "@set"
    },
    "seeAlso": {
      "@id": "rdfs:seeAlso",
      "@container": "@set"
    }
  }
}