{
  "id": "https://www.w3id.org/KulturVok/terms/grobsystematik/FDF89B",
  "type": "Concept",
  "prefLabel": {
    "de": "Blankwaffen"
  },
  "notation": [
    "FDF89B"
  ],
  "narrower": [
    {
      "id": "https://www.w3id.org/KulturVok/terms/grobsystematik/A352B4",
      "prefLabel": {
        "de": "Flamberger"
      }
    },
    {
      "id": "https://www.w3id.org/KulturVok/terms/grobsystematik/A53C53",
      "prefLabel": {
        "de": "Artilleriedegen"
      }
    },
    {
      "id": "https://www.w3id.org/KulturVok/terms/grobsystematik/A6115F",
      "prefLabel": {
        "de": "Partisane"
      }
    },
    {
      "id": "https://www.w3id.org/KulturVok/terms/grobsystematik/A63652",
      "prefLabel": {
        "de": "Reiterdegen"
      }
    },
    {
      "id": "https://www.w3id.org/KulturVok/terms/grobsystematik/A6BFGB",
      "prefLabel": {
        "de": "Vortrageschwert"
      }
    },
    {
      "id": "https://www.w3id.org/KulturVok/terms/grobsystematik/ACGCC4",
      "prefLabel": {
        "de": "Pallasch"
      }
    },
    {
      "id": "https://www.w3id.org/KulturVok/terms/grobsystematik/B1671A",
      "prefLabel": {
        "de": "Fechtdegen"
      }
    },
    {
      "id": "https://www.w3id.org/KulturVok/terms/grobsystematik/B4FGA6",
      "prefLabel": {
        "de": "Speer"
      }
    },
    {
      "id": "https://www.w3id.org/KulturVok/terms/grobsystematik/B4G821",
      "prefLabel": {
        "de": "Bihänder"
      }
    },
    {
      "id": "https://www.w3id.org/KulturVok/terms/grobsystematik/B817D4",
      "prefLabel": {
        "de": "Aufpflanzbajonett"
      }
    },
    {
      "id": "https://www.w3id.org/KulturVok/terms/grobsystematik/B8CGF7",
      "prefLabel": {
        "de": "Kavalleriepallasch"
      }
    },
    {
      "id": "https://www.w3id.org/KulturVok/terms/grobsystematik/BBBB26",
      "prefLabel": {
        "de": "Sponton"
      }
    },
    {
      "id": "https://www.w3id.org/KulturVok/terms/grobsystematik/BC2322",
      "prefLabel": {
        "de": "Krummsäbel"
      }
    },
    {
      "id": "https://www.w3id.org/KulturVok/terms/grobsystematik/BC8786",
      "prefLabel": {
        "de": "Langschwert"
      }
    },
    {
      "id": "https://www.w3id.org/KulturVok/terms/grobsystematik/BD2GDB",
      "prefLabel": {
        "de": "Jagdspieß"
      }
    },
    {
      "id": "https://www.w3id.org/KulturVok/terms/grobsystematik/BG69AC",
      "prefLabel": {
        "de": "Kurzschwert"
      }
    },
    {
      "id": "https://www.w3id.org/KulturVok/terms/grobsystematik/C7DA1D",
      "prefLabel": {
        "de": "Degen"
      }
    },
    {
      "id": "https://www.w3id.org/KulturVok/terms/grobsystematik/C7F527",
      "prefLabel": {
        "de": "Schwert"
      }
    },
    {
      "id": "https://www.w3id.org/KulturVok/terms/grobsystematik/C8118D",
      "prefLabel": {
        "de": "Dolch"
      }
    },
    {
      "id": "https://www.w3id.org/KulturVok/terms/grobsystematik/C92911",
      "prefLabel": {
        "de": "Infanterieseitengewehr"
      }
    },
    {
      "id": "https://www.w3id.org/KulturVok/terms/grobsystematik/CAB34D",
      "prefLabel": {
        "de": "Stichwaffe"
      }
    },
    {
      "id": "https://www.w3id.org/KulturVok/terms/grobsystematik/CC9391",
      "prefLabel": {
        "de": "Bajonett"
      }
    },
    {
      "id": "https://www.w3id.org/KulturVok/terms/grobsystematik/CDA41B",
      "prefLabel": {
        "de": "Schutzspeer"
      }
    },
    {
      "id": "https://www.w3id.org/KulturVok/terms/grobsystematik/D19D49",
      "prefLabel": {
        "de": "Bronze-Kurzschwert"
      }
    },
    {
      "id": "https://www.w3id.org/KulturVok/terms/grobsystematik/D239CD",
      "prefLabel": {
        "de": "Säbel"
      }
    },
    {
      "id": "https://www.w3id.org/KulturVok/terms/grobsystematik/D35F6F",
      "prefLabel": {
        "de": "Reitersäbel"
      }
    },
    {
      "id": "https://www.w3id.org/KulturVok/terms/grobsystematik/D3C212",
      "prefLabel": {
        "de": "Offizierssäbel"
      }
    },
    {
      "id": "https://www.w3id.org/KulturVok/terms/grobsystematik/D86834",
      "prefLabel": {
        "de": "Saufeder"
      }
    },
    {
      "id": "https://www.w3id.org/KulturVok/terms/grobsystematik/DC8CF5",
      "prefLabel": {
        "de": "Schleppdegen"
      }
    },
    {
      "id": "https://www.w3id.org/KulturVok/terms/grobsystematik/DF9D8B",
      "prefLabel": {
        "de": "Lanze"
      }
    },
    {
      "id": "https://www.w3id.org/KulturVok/terms/grobsystematik/F43AGC",
      "prefLabel": {
        "de": "Kurzdegen"
      }
    },
    {
      "id": "https://www.w3id.org/KulturVok/terms/grobsystematik/F69441",
      "prefLabel": {
        "de": "Seitengewehr"
      }
    },
    {
      "id": "https://www.w3id.org/KulturVok/terms/grobsystematik/F749D3",
      "prefLabel": {
        "de": "Helmbarte"
      }
    },
    {
      "id": "https://www.w3id.org/KulturVok/terms/grobsystematik/F76GA2",
      "prefLabel": {
        "de": "Füseliersäbel"
      }
    },
    {
      "id": "https://www.w3id.org/KulturVok/terms/grobsystematik/F7B3BD",
      "prefLabel": {
        "de": "Ordonanzstichdegen"
      }
    },
    {
      "id": "https://www.w3id.org/KulturVok/terms/grobsystematik/F8C44G",
      "prefLabel": {
        "de": "Spandolch"
      }
    },
    {
      "id": "https://www.w3id.org/KulturVok/terms/grobsystematik/FBFB1F",
      "prefLabel": {
        "de": "Füselierseitengewehr"
      }
    },
    {
      "id": "https://www.w3id.org/KulturVok/terms/grobsystematik/FC434F",
      "prefLabel": {
        "de": "Hellebarde"
      }
    },
    {
      "id": "https://www.w3id.org/KulturVok/terms/grobsystematik/FD7B7A",
      "prefLabel": {
        "de": "Tüllenbajonett"
      }
    },
    {
      "id": "https://www.w3id.org/KulturVok/terms/grobsystematik/FF1GF2",
      "prefLabel": {
        "de": "Zierdegen"
      }
    },
    {
      "id": "https://www.w3id.org/KulturVok/terms/grobsystematik/FFC2D5",
      "prefLabel": {
        "de": "Spieß"
      }
    },
    {
      "id": "https://www.w3id.org/KulturVok/terms/grobsystematik/FG3DGG",
      "prefLabel": {
        "de": "Eisen-Säbel"
      }
    },
    {
      "id": "https://www.w3id.org/KulturVok/terms/grobsystematik/G4B115",
      "prefLabel": {
        "de": "Eisen-Hellebarde"
      }
    },
    {
      "id": "https://www.w3id.org/KulturVok/terms/grobsystematik/G62BB3",
      "prefLabel": {
        "de": "Hirschfänger"
      }
    },
    {
      "id": "https://www.w3id.org/KulturVok/terms/grobsystematik/G74A7B",
      "prefLabel": {
        "de": "Kavalleriedegen"
      }
    },
    {
      "id": "https://www.w3id.org/KulturVok/terms/grobsystematik/G895C5",
      "prefLabel": {
        "de": "Offiziersdegen"
      }
    },
    {
      "id": "https://www.w3id.org/KulturVok/terms/grobsystematik/GB3346",
      "prefLabel": {
        "de": "Kavalleriesäbel"
      }
    }
  ],
  "broader": {
    "id": "https://www.w3id.org/KulturVok/terms/grobsystematik/GB67C3",
    "prefLabel": {
      "de": "Waffen"
    }
  },
  "inScheme": [
    {
      "id": "https://www.w3id.org/KulturVok/terms/grobsystematik",
      "title": {
        "de": "Grobsystematik"
      }
    }
  ],
  "inSchemeAll": [
    {
      "id": "https://www.w3id.org/KulturVok/terms/grobsystematik"
    }
  ],
  "@context": {
    "@version": 1.1,
    "id": "@id",
    "type": "@type",
    "@vocab": "http://www.w3.org/2004/02/skos/core#",
    "xsd": "http://www.w3.org/2001/XMLSchema#",
    "dct": "http://purl.org/dc/terms/",
    "dc": "http://purl.org/dc/elements/1.1/",
    "schema": "https://schema.org/",
    "vann": "http://purl.org/vocab/vann/",
    "ldp": "http://www.w3.org/ns/ldp#",
    "owl": "http://www.w3.org/2002/07/owl#",
    "rdfs": "http://www.w3.org/2000/01/rdf-schema#",
    "ex": "http://www.example.com/",
    "title": {
      "@id": "dct:title",
      "@container": "@language"
    },
    "dc:title": {
      "@id": "dc:title",
      "@container": "@language"
    },
    "dc:description": {
      "@id": "dc:description",
      "@container": "@language"
    },
    "description": {
      "@id": "dct:description",
      "@container": "@language"
    },
    "license": {
      "@id": "dct:license",
      "@container": "@language"
    },
    "issued": {
      "@id": "dct:issued",
      "@type": "xsd:date"
    },
    "created": {
      "@id": "dct:created",
      "@type": "xsd:date"
    },
    "modified": {
      "@id": "dct:modified",
      "@type": "xsd:date"
    },
    "creator": {
      "@id": "dct:creator",
      "@container": "@set"
    },
    "contributor": {
      "@id": "dct:contributor",
      "@container": "@set"
    },
    "subject": {
      "@id": "dct:subject",
      "@container": [
        "@language",
        "@set"
      ]
    },
    "rights": {
      "@id": "dct:rights",
      "@container": "@set"
    },
    "publisher": "dct:publisher",
    "preferredNamespacePrefix": "vann:preferredNamespacePrefix",
    "preferredNamespaceUri": "vann:preferredNamespaceUri",
    "isBasedOn": "schema:isBasedOn",
    "conceptCount": "ex:conceptCount",
    "source": {
      "@id": "dct:source",
      "@container": "@set"
    },
    "prefLabel": {
      "@container": "@language"
    },
    "altLabel": {
      "@container": [
        "@language",
        "@set"
      ]
    },
    "hiddenLabel": {
      "@container": [
        "@language",
        "@set"
      ]
    },
    "definition": {
      "@container": "@language"
    },
    "note": {
      "@container": [
        "@language",
        "@set"
      ]
    },
    "changeNote": {
      "@container": [
        "@language",
        "@set"
      ]
    },
    "editorialNote": {
      "@container": [
        "@language",
        "@set"
      ]
    },
    "historyNote": {
      "@container": [
        "@language",
        "@set"
      ]
    },
    "scopeNote": {
      "@container": [
        "@language",
        "@set"
      ]
    },
    "notation": {
      "@container": "@set"
    },
    "example": {
      "@container": "@language"
    },
    "narrower": {
      "@container": "@set"
    },
    "related": {
      "@container": "@set"
    },
    "relatedMatch": {
      "@container": "@set"
    },
    "narrowerTransitive": {
      "@container": "@set"
    },
    "broaderTransitive": {
      "@container": "@set"
    },
    "broadMatch": {
      "@container": "@set"
    },
    "narrowMatch": {
      "@container": "@set"
    },
    "closeMatch": {
      "@container": "@set"
    },
    "exactMatch": {
      "@container": "@set"
    },
    "hasTopConcept": {
      "@container": "@set"
    },
    "inScheme": {
      "@container": "@set"
    },
    "topConceptOf": {
      "@container": "@set"
    },
    "deprecated": {
      "@id": "owl:deprecated",
      "@type": "xsd:boolean"
    },
    "isReplacedBy": {
      "@id": "dct:isReplacedBy",
      "@container": "@set"
    },
    "seeAlso": {
      "@id": "rdfs:seeAlso",
      "@container": "@set"
    }
  }
}